YetAnotherPicSearch/__init__.py
YetAnotherPicSearch/__main__.py
YetAnotherPicSearch/cache.py
YetAnotherPicSearch/config.py
YetAnotherPicSearch/nhentai_model.py
YetAnotherPicSearch/registry.py
YetAnotherPicSearch/utils.py
YetAnotherPicSearch/data_source/__init__.py
YetAnotherPicSearch/data_source/ascii2d.py
YetAnotherPicSearch/data_source/baidu.py
YetAnotherPicSearch/data_source/ehentai.py
YetAnotherPicSearch/data_source/google.py
YetAnotherPicSearch/data_source/iqdb.py
YetAnotherPicSearch/data_source/nhentai.py
YetAnotherPicSearch/data_source/saucenao.py
YetAnotherPicSearch/data_source/whatanime.py
YetAnotherPicSearch/data_source/yandex.py
YetAnotherPicSearch/res/usage.jpg
yetanotherpicsearch-2.0.10.dist-info/METADATA
yetanotherpicsearch-2.0.10.dist-info/WHEEL
yetanotherpicsearch-2.0.10.dist-info/licenses/LICENSE
yetanotherpicsearch-2.0.10.dist-info/RECORD
