Metadata-Version: 2.4
Name: YetAnotherPicSearch
Version: 2.0.10
Summary: Yet Another Picture Search Nonebot Plugin
Project-URL: homepage, https://github.com/lgc-NB2Dev/YetAnotherPicSearch
Project-URL: repository, https://github.com/lgc-NB2Dev/YetAnotherPicSearch
Author: NekoAria
Author-email: LgCookie <lgc2333@126.com>
License: GPL-3.0-only
License-File: LICENSE
Keywords: anime,ascii2d,baidu,danbooru,doujin,e-hentai,google,iqdb,nonebot,pixiv,saucenao,tracemoe,yandex
Requires-Python: >=3.10
Requires-Dist: arrow>=1.3.0
Requires-Dist: cookit[loguru,nonebot-alconna,pydantic]>=0.13.2
Requires-Dist: httpx>=0.28.1
Requires-Dist: lxml>=5.4.0
Requires-Dist: msgpack>=1.1.1
Requires-Dist: nonebot-plugin-alconna>=0.59.4
Requires-Dist: nonebot-plugin-waiter>=0.8.1
Requires-Dist: nonebot2>=2.4.3
Requires-Dist: picimagesearch>=3.12.11
Requires-Dist: pillow>=11.3.0
Requires-Dist: pyquery>=2.0.1
Requires-Dist: tenacity>=9.1.2
Provides-Extra: all
Requires-Dist: httpx[socks]>=0.27.2; extra == 'all'
Provides-Extra: socks
Requires-Dist: httpx[socks]>=0.27.2; extra == 'socks'
